comfyui_manager/__init__.py
comfyui_manager/alter-list.json
comfyui_manager/channels.list.template
comfyui_manager/custom-node-list.json
comfyui_manager/extension-node-map.json
comfyui_manager/extras.json
comfyui_manager/github-stats.json
comfyui_manager/model-list.json
comfyui_manager/prestartup_script.py
comfyui_manager/cm_cli/__init__.py
comfyui_manager/cm_cli/__main__.py
comfyui_manager/common/__init__.py
comfyui_manager/common/cm_global.py
comfyui_manager/common/cnr_utils.py
comfyui_manager/common/context.py
comfyui_manager/common/enums.py
comfyui_manager/common/git_helper.py
comfyui_manager/common/git_utils.py
comfyui_manager/common/manager_downloader.py
comfyui_manager/common/manager_security.py
comfyui_manager/common/manager_util.py
comfyui_manager/common/node_package.py
comfyui_manager/common/security_check.py
comfyui_manager/common/timestamp_utils.py
comfyui_manager/data_models/__init__.py
comfyui_manager/data_models/generated_models.py
comfyui_manager/glob/CLAUDE.md
comfyui_manager/glob/__init__.py
comfyui_manager/glob/constants.py
comfyui_manager/glob/manager_core.py
comfyui_manager/glob/manager_server.py
comfyui_manager/glob/share_3rdparty.py
comfyui_manager/glob/utils/__init__.py
comfyui_manager/glob/utils/environment_utils.py
comfyui_manager/glob/utils/formatting_utils.py
comfyui_manager/glob/utils/model_utils.py
comfyui_manager/glob/utils/node_pack_utils.py
comfyui_manager/glob/utils/security_utils.py
comfyui_manager/js/README.md
comfyui_manager/js/cm-api.js
comfyui_manager/js/comfyui-gui-builder.js
comfyui_manager/js/comfyui-manager.js
comfyui_manager/js/comfyui-share-common.js
comfyui_manager/js/comfyui-share-copus.js
comfyui_manager/js/comfyui-share-openart.js
comfyui_manager/js/comfyui-share-youml.js
comfyui_manager/js/common.js
comfyui_manager/js/custom-nodes-manager.css
comfyui_manager/js/custom-nodes-manager.js
comfyui_manager/js/model-manager.css
comfyui_manager/js/model-manager.js
comfyui_manager/js/node_fixer.js
comfyui_manager-4.0.5.dist-info/licenses/LICENSE.txt
comfyui_manager-4.0.5.dist-info/METADATA
comfyui_manager-4.0.5.dist-info/WHEEL
comfyui_manager-4.0.5.dist-info/entry_points.txt
comfyui_manager-4.0.5.dist-info/top_level.txt
comfyui_manager-4.0.5.dist-info/RECORD
