Metadata-Version: 2.4
Name: comfyui-manager
Version: 4.0.5
Summary: ComfyUI-Manager provides features to install and manage custom nodes for ComfyUI, as well as various functionalities to assist with ComfyUI.
Maintainer-email: "Dr.Lt.Data" <dr.lt.data@gmail.com>, Yoland Yan <yoland@comfy.org>, James Kwon <hongilkwon316@gmail.com>, Robin Huang <robin@comfy.org>
License: GPL-3.0-only
Project-URL: Repository, https://github.com/ltdrdata/ComfyUI-Manager
Keywords: comfyui,comfyui-manager
Classifier: Development Status :: 5 - Production/Stable
Classifier: Intended Audience :: Developers
Classifier: License :: OSI Approved :: GNU General Public License v3 (GPLv3)
Requires-Python: >=3.9
License-File: LICENSE.txt
Requires-Dist: GitPython
Requires-Dist: PyGithub
Requires-Dist: transformers
Requires-Dist: huggingface-hub>0.20
Requires-Dist: typer
Requires-Dist: rich
Requires-Dist: typing-extensions
Requires-Dist: toml
Requires-Dist: uv
Requires-Dist: chardet
Provides-Extra: dev
Requires-Dist: pre-commit; extra == "dev"
Requires-Dist: pytest; extra == "dev"
Requires-Dist: ruff; extra == "dev"
Requires-Dist: pytest-cov; extra == "dev"
Dynamic: license-file
